django_press/__init__.py
django_press/apps.py
django_press/urls.py
django_press/__pycache__/__init__.cpython-36.pyc
django_press/__pycache__/__init__.cpython-38.pyc
django_press/__pycache__/apps.cpython-36.pyc
django_press/__pycache__/apps.cpython-38.pyc
django_press/__pycache__/urls.cpython-36.pyc
django_press/__pycache__/urls.cpython-38.pyc
django_press/admin/Inquiry.py
django_press/admin/__init__.py
django_press/admin/context.py
django_press/admin/page.py
django_press/admin/__pycache__/Inquiry.cpython-36.pyc
django_press/admin/__pycache__/Inquiry.cpython-38.pyc
django_press/admin/__pycache__/__init__.cpython-36.pyc
django_press/admin/__pycache__/__init__.cpython-38.pyc
django_press/admin/__pycache__/context.cpython-36.pyc
django_press/admin/__pycache__/context.cpython-38.pyc
django_press/admin/__pycache__/page.cpython-36.pyc
django_press/admin/__pycache__/page.cpython-38.pyc
django_press/middleware/__init__.py
django_press/middleware/rendering.py
django_press/middleware/__pycache__/__init__.cpython-36.pyc
django_press/middleware/__pycache__/__init__.cpython-38.pyc
django_press/middleware/__pycache__/rendering.cpython-36.pyc
django_press/middleware/__pycache__/rendering.cpython-38.pyc
django_press/migrations/0001_initial.py
django_press/migrations/0002_auto_20191220_0223.py
django_press/migrations/0003_auto_20191220_0352.py
django_press/migrations/0004_auto_20191220_0400.py
django_press/migrations/0005_auto_20191220_0421.py
django_press/migrations/0006_auto_20191220_0422.py
django_press/migrations/0007_contactcontent_success_page.py
django_press/migrations/0008_tab_name.py
django_press/migrations/0009_page_publish.py
django_press/migrations/__init__.py
django_press/migrations/__pycache__/0001_initial.cpython-36.pyc
django_press/migrations/__pycache__/0001_initial.cpython-38.pyc
django_press/migrations/__pycache__/0002_auto_20191220_0223.cpython-36.pyc
django_press/migrations/__pycache__/0002_auto_20191220_0223.cpython-38.pyc
django_press-0.1.13.dist-info/METADATA
django_press-0.1.13.dist-info/WHEEL
django_press-0.1.13.dist-info/top_level.txt
django_press-0.1.13.dist-info/RECORD
