Metadata-Version: 2.1
Name: django-press
Version: 0.1.13
Summary: Easy start web app without coding
Home-page: https://github.com/YutaUra/YCU-Programing/tree/master/Code_Review/ura_1
Author: Yuta Ura
Author-email: yuuta3594@outlook.jp
License: MIT License
Platform: UNKNOWN
Classifier: Development Status :: 2 - Pre-Alpha
Classifier: Environment :: Web Environment
Classifier: Framework :: Django
Classifier: Framework :: Django :: 2.2
Classifier: Intended Audience :: Developers
Classifier: License :: OSI Approved :: MIT License
Classifier: Natural Language :: Japanese
Classifier: Operating System :: OS Independent
Classifier: Programming Language :: Python
Classifier: Programming Language :: Python :: 3
Classifier: Programming Language :: Python :: 3.6
Requires-Dist: django-markdownx
Requires-Dist: django-polymorphic
